auto_pull_request/__init__.py
auto_pull_request/content.py
auto_pull_request/git.py
auto_pull_request/parser.py
auto_pull_request/pull_request.py
auto_pull_request/utility.py
auto_pull_request-7.1.23.dist-info/entry_points.txt
auto_pull_request-7.1.23.dist-info/LICENSE
auto_pull_request-7.1.23.dist-info/WHEEL
auto_pull_request-7.1.23.dist-info/METADATA
auto_pull_request-7.1.23.dist-info/RECORD
