Metadata-Version: 2.1
Name: auto-pull-request
Version: 7.1.23
Summary: 
Author: ruth-seven
Author-email: 1098057570@qq.com
Requires-Python: >=3.6,<4.0
Classifier: Programming Language :: Python :: 3
Classifier: Programming Language :: Python :: 3.6
Classifier: Programming Language :: Python :: 3.7
Classifier: Programming Language :: Python :: 3.8
Classifier: Programming Language :: Python :: 3.9
Requires-Dist: PyGithub (>=1.55,<2.0)
Requires-Dist: attrs (>=21.2.0,<22.0.0)
Requires-Dist: click (>=8.0.1,<9.0.0)
Requires-Dist: loguru (>=0.5.3,<0.6.0)
Requires-Dist: poetry-dynamic-versioning (==0.13.1)
